dmdm/__init__.py
dmdm/mail.py
dmdm/py.typed
dmdm-3.0.0.dist-info/WHEEL
dmdm-3.0.0.dist-info/METADATA
dmdm-3.0.0.dist-info/RECORD
