Metadata-Version: 2.4
Name: dmdm
Version: 3.0.0
Summary: Django MarkDown Mails
Author: Guilhem Saurel
Author-email: Guilhem Saurel <guilhem.saurel@laas.fr>
License-Expression: BSD-2-Clause
Requires-Dist: django>=5.1.6
Requires-Dist: nmdmail>=0.4.0
Requires-Python: >=3.10
Project-URL: changelog, https://github.com/nim65s/dmdm/blob/main/CHANGELOG.md
Project-URL: homepage, https://github.com/nim65s/dmdm
Project-URL: repository, https://github.com/nim65s/dmdm.git
